jelloow_names/__init__.py
jelloow_names/names.py
jelloow_names/urls.py
jelloow_names-0.0.9.dist-info/METADATA
jelloow_names-0.0.9.dist-info/WHEEL
jelloow_names-0.0.9.dist-info/RECORD
