Metadata-Version: 2.1
Name: jelloow_names
Version: 0.0.9
Summary: Package for maintaining centralized goverance of data for company data extraction
Author-email: Michael Lucky <michael@llab.dev>
Classifier: Operating System :: OS Independent
Classifier: Programming Language :: Python :: 3
Requires-Python: >=3.11
